{
  "skill": "listening",
  "content": {
    "audioUrl": "https://luyenthivstep.vn/assets/nhch/listening/bac3/lp2-1664818798_f74880ea7d9b192794b0.mp3",
    "items": [
      {
        "stem": "Question 1",
        "options": [
          "She has toothache.",
          "She has headache.",
          "He has coughs.",
          "She has stomachache."
        ]
      },
      {
        "stem": "Question 2",
        "options": [
          "It makes them funny.",
          "It makes them happy.",
          "It makes them excited.",
          "It makes them annoyed."
        ]
      },
      {
        "stem": "Question 3",
        "options": [
          "She had headache.",
          "She had a fall off her bike.",
          "She had stomachache.",
          "She had coughs."
        ]
      },
      {
        "stem": "Question 4",
        "options": [
          "She has temperature.",
          "She has backache.",
          "She has headache.",
          "She has toothache."
        ]
      },
      {
        "stem": "Question 5",
        "options": [
          "Because he feels hot staying at home.",
          "Because he feels safe staying at home.",
          "Because he feels bored staying at home.",
          "Because he feels cold staying at home."
        ]
      },
      {
        "stem": "Question 6",
        "options": [
          "Because she has toothache.",
          "Because she has coughs.",
          "Because she has stomach ache.",
          "Because she feels tired."
        ]
      },
      {
        "stem": "Question 7",
        "options": [
          "Because she is short of money.",
          "Because she has stomachache.",
          "Because she's afraid she will fall asleep watching it.",
          "Because she is serious about it."
        ]
      },
      {
        "stem": "Question 8",
        "options": [
          "Because she doesn't want to watch it the second time.",
          "Because she feels too busy to watch it.",
          "Because she doesn't want to watch it the third time.",
          "Because she feels too serious to watch it."
        ]
      },
      {
        "stem": "Question 9",
        "options": [
          "It may be cheap.",
          "It may be very expensive.",
          "It may be very cheap.",
          "It may be expensive."
        ]
      },
      {
        "stem": "Question 10",
        "options": [
          "Because he doesn't like hard work.",
          "Because she doesn't like the sounds of people walking.",
          "Because he feels too hot to do it.",
          "Because he finds it hard to do it."
        ]
      },
      {
        "stem": "Question 11",
        "options": [
          "It is sometimes good.",
          "It is clean and cheap.",
          "It is comfortable.",
          "It is good."
        ]
      },
      {
        "stem": "Question 12",
        "options": [
          "leave home.",
          "sell his home.",
          "enjoy his holiday home.",
          "go home."
        ]
      }
    ]
  },
  "answerKey": {
    "correctAnswers": {
      "1": "2",
      "2": "3",
      "3": "1",
      "4": "0",
      "5": "2",
      "6": "3",
      "7": "2",
      "8": "0",
      "9": "0",
      "10": "3",
      "11": "1",
      "12": "3"
    }
  },
  "metadata": {
    "source": "crawled",
    "sourceUrl": "https://luyenthivstep.vn/luyen-de/lam-bai-nghe/8",
    "examId": 8
  },
  "part": 1
}
